defender/__init__.py
defender-0.0.3.dist-info/LICENSE
defender-0.0.3.dist-info/METADATA
defender-0.0.3.dist-info/WHEEL
defender-0.0.3.dist-info/top_level.txt
defender-0.0.3.dist-info/RECORD
